MANIFEST.in
README.rst
setup.cfg
setup.py
flickrapi/__init__.py
flickrapi/__init__.pyc
flickrapi/cache.py
flickrapi/cache.pyc
flickrapi/exceptions.py
flickrapi/exceptions.pyc
flickrapi/multipart.py
flickrapi/multipart.pyc
flickrapi/reportinghttp.py
flickrapi/reportinghttp.pyc
flickrapi/shorturl.py
flickrapi/tokencache.py
flickrapi/tokencache.pyc
flickrapi/xmlnode.py
flickrapi/xmlnode.pyc
flickrsmartsync/__init__.py
flickrsmartsync/__main__.py
flickrsmartsync/local.py
flickrsmartsync/remote.py
flickrsmartsync/sync.py
flickrsmartsync.egg-info/PKG-INFO
flickrsmartsync.egg-info/SOURCES.txt
flickrsmartsync.egg-info/dependency_links.txt
flickrsmartsync.egg-info/entry_points.txt
flickrsmartsync.egg-info/not-zip-safe
flickrsmartsync.egg-info/pbr.json
flickrsmartsync.egg-info/requires.txt
flickrsmartsync.egg-info/top_level.txt
test/test_local.py
test/test_remote.py
test/test_sync.py