Metadata-Version: 1.1
Name: flickrsmartsync
Version: 0.2.01-r0
Summary: Sync/backup your photos to flickr easily
Home-page: https://github.com/faisalraja/flickrsmartsync
Author: Faisal Raja
Author-email: support@altlimit.com
License: MIT
Keywords: flickr backup photo sync
Platform: UNKNOWN
Classifier: Development Status :: 3 - Alpha
Classifier: Environment :: Console
Classifier: Programming Language :: Python
Classifier: License :: OSI Approved :: MIT License
